django_sqlprint_middleware/__init__.py
django_sqlprint_middleware/django_sqlprint_middleware.py
django_sqlprint_middleware-0.1.4.dist-info/LICENSE
django_sqlprint_middleware-0.1.4.dist-info/METADATA
django_sqlprint_middleware-0.1.4.dist-info/WHEEL
django_sqlprint_middleware-0.1.4.dist-info/top_level.txt
django_sqlprint_middleware-0.1.4.dist-info/RECORD
