Metadata-Version: 2.1
Name: django-sqlprint-middleware
Version: 0.1.4
Summary: Pretty print Django's SQL statments
Home-page: https://github.com/thebjorn/django-sqlprint-middleware
Author: bjorn
Author-email: bp@datakortet.no
License: MIT
Platform: UNKNOWN
Classifier: Intended Audience :: Developers
Classifier: Natural Language :: English
Classifier: License :: OSI Approved :: MIT License
Classifier: Operating System :: OS Independent
Classifier: Programming Language :: Python
Classifier: Programming Language :: Python :: 2
Classifier: Programming Language :: Python :: 2.7
Classifier: Programming Language :: Python :: 3
Classifier: Topic :: Software Development :: Libraries :: Python Modules
Classifier: Framework :: Django
Requires-Dist: pygments-pprint-sql
Requires-Dist: Django
